[
  {
    "keyword": "아르테미스 2호 지구 귀환",
    "timestamp": "2026-04-24T11:02:12.371040",
    "sentiment": {
      "positive": 50,
      "negative": 50
    },
    "summary": [
      "데이터가 부족하여 요약할 수 없습니다.",
      "",
      ""
    ],
    "sources": []
  },
  {
    "keyword": "고유가 지원금",
    "timestamp": "2026-04-24T11:02:14.585385",
    "sentiment": {
      "positive": 50,
      "negative": 50
    },
    "summary": [
      "데이터가 부족하여 요약할 수 없습니다.",
      "",
      ""
    ],
    "sources": []
  },
  {
    "keyword": "아이유 변우석",
    "timestamp": "2026-04-24T11:02:16.790263",
    "sentiment": {
      "positive": 50,
      "negative": 50
    },
    "summary": [
      "데이터가 부족하여 요약할 수 없습니다.",
      "",
      ""
    ],
    "sources": []
  },
  {
    "keyword": "이정후 첫 홈런",
    "timestamp": "2026-04-24T11:02:19.017550",
    "sentiment": {
      "positive": 50,
      "negative": 50
    },
    "summary": [
      "데이터가 부족하여 요약할 수 없습니다.",
      "",
      ""
    ],
    "sources": []
  },
  {
    "keyword": "세미파이브",
    "timestamp": "2026-04-24T11:02:21.219723",
    "sentiment": {
      "positive": 50,
      "negative": 50
    },
    "summary": [
      "데이터가 부족하여 요약할 수 없습니다.",
      "",
      ""
    ],
    "sources": []
  },
  {
    "keyword": "몬테네그로",
    "timestamp": "2026-04-24T11:02:23.469352",
    "sentiment": {
      "positive": 50,
      "negative": 50
    },
    "summary": [
      "데이터가 부족하여 요약할 수 없습니다.",
      "",
      ""
    ],
    "sources": []
  },
  {
    "keyword": "김민석 총리 국무회의",
    "timestamp": "2026-04-24T11:02:25.674212",
    "sentiment": {
      "positive": 50,
      "negative": 50
    },
    "summary": [
      "데이터가 부족하여 요약할 수 없습니다.",
      "",
      ""
    ],
    "sources": []
  },
  {
    "keyword": "이스라엘 인권",
    "timestamp": "2026-04-24T11:02:27.878142",
    "sentiment": {
      "positive": 50,
      "negative": 50
    },
    "summary": [
      "데이터가 부족하여 요약할 수 없습니다.",
      "",
      ""
    ],
    "sources": []
  },
  {
    "keyword": "손종원",
    "timestamp": "2026-04-24T11:02:30.098041",
    "sentiment": {
      "positive": 50,
      "negative": 50
    },
    "summary": [
      "데이터가 부족하여 요약할 수 없습니다.",
      "",
      ""
    ],
    "sources": []
  },
  {
    "keyword": "이재명 폴란드 정상회담",
    "timestamp": "2026-04-24T11:02:32.293233",
    "sentiment": {
      "positive": 50,
      "negative": 50
    },
    "summary": [
      "데이터가 부족하여 요약할 수 없습니다.",
      "",
      ""
    ],
    "sources": []
  }
]